{
  "nunaliit_type": "atlas",
  "title": "Atlas Title",
  "nunaliit_navigation": {
    "nunaliit_type": "navigation",
    "title": {
      "nunaliit_type": "localized",
      "en": "Atlas",
      "fr": "L'Atlas"
    },
    "items": [
      {
        "title": {
          "nunaliit_type": "localized",
          "en": "Default Module",
          "fr": "Module de Base"
        },
        "module": "module.demo",
        "items": [
          {
            "module": "module.demo"
          }
        ]
      },
      {
        "title": {
          "nunaliit_type": "localized",
          "en": "Tools",
          "fr": "Outils"
        },
        "href": "./tools/index.html"
      }
    ]
  },
  "nunaliit_metadata": {
    "license": "",
    "creator": {
      "contactPoint": {
        "@type": "ContactPoint",
        "contactType": "",
        "telephone": "",
        "email": ""
      },
      "@type": "Organization",
      "name": "",
      "url": ""
    },
    "dateCreated": "",
    "keywords": [
    ],
    "temporalCoverage": "",
    "@type": "Dataset",
    "name": "",
    "description": "",
    "spatialCoverage": {
      "geo": {
        "@type": "GeoShape",
        "box": ""
      },
      "@type": "Place"
    },
    "@context": {
      "@vocab": "http://schema.org"
    },
    "url": ""
  }
}
